paper_down/__init__.py
paper_down/downloader.py
paper_down/main.py
paper_down/save.py
paper_down/config/__init__.py
paper_down/config/config_loader.py
paper_downloader-1.0.2.dist-info/LICENSE
paper_downloader-1.0.2.dist-info/METADATA
paper_downloader-1.0.2.dist-info/WHEEL
paper_downloader-1.0.2.dist-info/entry_points.txt
paper_downloader-1.0.2.dist-info/top_level.txt
paper_downloader-1.0.2.dist-info/RECORD
