Metadata-Version: 2.1
Name: paper-downloader
Version: 1.0.2
Summary: Download, Merge, and Rename
Home-page: https://github.com/dw-dengwei/paper-down
Author: Wei Deng
Author-email: dw-dengwei@outlook.com
Classifier: Programming Language :: Python :: 3
Classifier: License :: OSI Approved :: MIT License
Classifier: Operating System :: OS Independent
Requires-Python: >=3.8
License-File: LICENSE
Requires-Dist: requests >=2.28.0
Requires-Dist: tqdm >=4.64.0
Requires-Dist: pypdf >=4.3.1
Requires-Dist: prompt-toolkit >=3.0.39
